CHANGELOG.md
CONTRIBUTING.md
LICENSE.txt
MANIFEST.in
README.md
requirements.in
setup.cfg
setup.py
streamdeck_manager/__init__.py
streamdeck_manager/_meta.py
streamdeck_manager/core.py
streamdeck_manager/deck.py
streamdeck_manager/entities.py
streamdeck_manager/panel.py
streamdeck_manager/utils.py
streamdeck_manager.egg-info/PKG-INFO
streamdeck_manager.egg-info/SOURCES.txt
streamdeck_manager.egg-info/dependency_links.txt
streamdeck_manager.egg-info/entry_points.txt
streamdeck_manager.egg-info/requires.txt
streamdeck_manager.egg-info/top_level.txt
streamdeck_manager/assets/Harold.jpg
streamdeck_manager/assets/Roboto-Regular.ttf
streamdeck_manager/assets/back.png
streamdeck_manager/assets/eject.png
streamdeck_manager/assets/error.png
streamdeck_manager/assets/folder.png
streamdeck_manager/assets/like.png
streamdeck_manager/assets/minus.png
streamdeck_manager/assets/next.png
streamdeck_manager/assets/play_button.png
streamdeck_manager/assets/plus.png
streamdeck_manager/assets/pressed.png
streamdeck_manager/assets/released.png
streamdeck_manager/assets/star.png
streamdeck_manager/assets/stop.png
streamdeck_manager/assets/success.png
streamdeck_manager/assets/warning.png
streamdeck_manager/assets/files/avi.png
streamdeck_manager/assets/files/bin.png
streamdeck_manager/assets/files/csv.png
streamdeck_manager/assets/files/exe.png
streamdeck_manager/assets/files/gif.png
streamdeck_manager/assets/files/git.png
streamdeck_manager/assets/files/ico.png
streamdeck_manager/assets/files/iso.png
streamdeck_manager/assets/files/jpg.png
streamdeck_manager/assets/files/mkv.png
streamdeck_manager/assets/files/mp3.png
streamdeck_manager/assets/files/mp4.png
streamdeck_manager/assets/files/obj.png
streamdeck_manager/assets/files/pdf.png
streamdeck_manager/assets/files/png.png
streamdeck_manager/assets/files/ppt.png
streamdeck_manager/assets/files/ttf.png
streamdeck_manager/assets/files/txt.png
streamdeck_manager/assets/files/wav.png
streamdeck_manager/assets/files/xml.png
streamdeck_manager/assets/files/zip.png
streamdeck_manager/assets/gif/Elephant_Walking_animated.gif
streamdeck_manager/assets/gif/RGB_color_space_animated_view.gif
streamdeck_manager/assets/gif/Simple_CV_Joint_animated.gif
