Metadata-Version: 2.1
Name: streamdeck-manager
Version: 0.2.0
Summary: Library to manage elgato stream deck in a easy way with several use cases implemented.
Home-page: https://github.com/vgonisanz/streamdeck_manager
Author: vgonisanz
Author-email: vgonisanz@gmail.com
License: MIT
Download-URL: https://github.com/vgonisanz/streamdeck_manager/archive/refs/tags/v0.1.0.tar.gz
Keywords: elgato,streamdeck,userfriendly,manager
Platform: any
Classifier: Development Status :: 5 - Production/Stable
Classifier: Intended Audience :: Developers
Classifier: Natural Language :: English
Classifier: License :: OSI Approved :: MIT License
Classifier: Programming Language :: Python :: 3
Classifier: Programming Language :: Python :: 3.7
Classifier: Programming Language :: Python :: Implementation :: PyPy
Requires-Python: >=3.6.*, <4
